{
    "description": "myFlix Theme",
    "seed": "#F84040",
    "coreColors": {
        "primary": "#F84040"
    },
    "extendedColors": [
        {
            "name": "Custom Color",
            "color": "#3F7EC7",
            "description": "",
            "harmonized": false
        }
    ],
    "schemes": {
        "light": {
            "primary": "#904A45",
            "surfaceTint": "#904A45",
            "onPrimary": "#FFFFFF",
            "primaryContainer": "#FFDAD6",
            "onPrimaryContainer": "#3B0908",
            "secondary": "#775653",
            "onSecondary": "#FFFFFF",
            "secondaryContainer": "#FFDAD6",
            "onSecondaryContainer": "#2C1513",
            "tertiary": "#725B2E",
            "onTertiary": "#FFFFFF",
            "tertiaryContainer": "#FFDEA6",
            "onTertiaryContainer": "#261900",
            "error": "#BA1A1A",
            "onError": "#FFFFFF",
            "errorContainer": "#FFDAD6",
            "onErrorContainer": "#410002",
            "background": "#FFF8F7",
            "onBackground": "#231918",
            "surface": "#FFF8F7",
            "onSurface": "#231918",
            "surfaceVariant": "#F5DDDB",
            "onSurfaceVariant": "#534342",
            "outline": "#857371",
            "outlineVariant": "#D8C2BF",
            "shadow": "#000000",
            "scrim": "#000000",
            "inverseSurface": "#392E2D",
            "inverseOnSurface": "#FFEDEB",
            "inversePrimary": "#FFB3AD",
            "primaryFixed": "#FFDAD6",
            "onPrimaryFixed": "#3B0908",
            "primaryFixedDim": "#FFB3AD",
            "onPrimaryFixedVariant": "#73332F",
            "secondaryFixed": "#FFDAD6",
            "onSecondaryFixed": "#2C1513",
            "secondaryFixedDim": "#E7BDB9",
            "onSecondaryFixedVariant": "#5D3F3D",
            "tertiaryFixed": "#FFDEA6",
            "onTertiaryFixed": "#261900",
            "tertiaryFixedDim": "#E1C28C",
            "onTertiaryFixedVariant": "#584319",
            "surfaceDim": "#E8D6D4",
            "surfaceBright": "#FFF8F7",
            "surfaceContainerLowest": "#FFFFFF",
            "surfaceContainerLow": "#FFF0EF",
            "surfaceContainer": "#FCEAE8",
            "surfaceContainerHigh": "#F6E4E2",
            "surfaceContainerHighest": "#F1DEDC"
        },
        "light-medium-contrast": {
            "primary": "#6E2F2C",
            "surfaceTint": "#904A45",
            "onPrimary": "#FFFFFF",
            "primaryContainer": "#AA5F5A",
            "onPrimaryContainer": "#FFFFFF",
            "secondary": "#593B39",
            "onSecondary": "#FFFFFF",
            "secondaryContainer": "#8F6C69",
            "onSecondaryContainer": "#FFFFFF",
            "tertiary": "#544015",
            "onTertiary": "#FFFFFF",
            "tertiaryContainer": "#8A7142",
            "onTertiaryContainer": "#FFFFFF",
            "error": "#8C0009",
            "onError": "#FFFFFF",
            "errorContainer": "#DA342E",
            "onErrorContainer": "#FFFFFF",
            "background": "#FFF8F7",
            "onBackground": "#231918",
            "surface": "#FFF8F7",
            "onSurface": "#231918",
            "surfaceVariant": "#F5DDDB",
            "onSurfaceVariant": "#4E3F3E",
            "outline": "#6C5B59",
            "outlineVariant": "#897675",
            "shadow": "#000000",
            "scrim": "#000000",
            "inverseSurface": "#392E2D",
            "inverseOnSurface": "#FFEDEB",
            "inversePrimary": "#FFB3AD",
            "primaryFixed": "#AA5F5A",
            "onPrimaryFixed": "#FFFFFF",
            "primaryFixedDim": "#8D4843",
            "onPrimaryFixedVariant": "#FFFFFF",
            "secondaryFixed": "#8F6C69",
            "onSecondaryFixed": "#FFFFFF",
            "secondaryFixedDim": "#745451",
            "onSecondaryFixedVariant": "#FFFFFF",
            "tertiaryFixed": "#8A7142",
            "onTertiaryFixed": "#FFFFFF",
            "tertiaryFixedDim": "#6F592C",
            "onTertiaryFixedVariant": "#FFFFFF",
            "surfaceDim": "#E8D6D4",
            "surfaceBright": "#FFF8F7",
            "surfaceContainerLowest": "#FFFFFF",
            "surfaceContainerLow": "#FFF0EF",
            "surfaceContainer": "#FCEAE8",
            "surfaceContainerHigh": "#F6E4E2",
            "surfaceContainerHighest": "#F1DEDC"
        },
        "light-high-contrast": {
            "primary": "#440F0E",
            "surfaceTint": "#904A45",
            "onPrimary": "#FFFFFF",
            "primaryContainer": "#6E2F2C",
            "onPrimaryContainer": "#FFFFFF",
            "secondary": "#341B1A",
            "onSecondary": "#FFFFFF",
            "secondaryContainer": "#593B39",
            "onSecondaryContainer": "#FFFFFF",
            "tertiary": "#2F2000",
            "onTertiary": "#FFFFFF",
            "tertiaryContainer": "#544015",
            "onTertiaryContainer": "#FFFFFF",
            "error": "#4E0002",
            "onError": "#FFFFFF",
            "errorContainer": "#8C0009",
            "onErrorContainer": "#FFFFFF",
            "background": "#FFF8F7",
            "onBackground": "#231918",
            "surface": "#FFF8F7",
            "onSurface": "#000000",
            "surfaceVariant": "#F5DDDB",
            "onSurfaceVariant": "#2E2120",
            "outline": "#4E3F3E",
            "outlineVariant": "#4E3F3E",
            "shadow": "#000000",
            "scrim": "#000000",
            "inverseSurface": "#392E2D",
            "inverseOnSurface": "#FFFFFF",
            "inversePrimary": "#FFE7E4",
            "primaryFixed": "#6E2F2C",
            "onPrimaryFixed": "#FFFFFF",
            "primaryFixedDim": "#521A18",
            "onPrimaryFixedVariant": "#FFFFFF",
            "secondaryFixed": "#593B39",
            "onSecondaryFixed": "#FFFFFF",
            "secondaryFixedDim": "#402624",
            "onSecondaryFixedVariant": "#FFFFFF",
            "tertiaryFixed": "#544015",
            "onTertiaryFixed": "#FFFFFF",
            "tertiaryFixedDim": "#3C2A02",
            "onTertiaryFixedVariant": "#FFFFFF",
            "surfaceDim": "#E8D6D4",
            "surfaceBright": "#FFF8F7",
            "surfaceContainerLowest": "#FFFFFF",
            "surfaceContainerLow": "#FFF0EF",
            "surfaceContainer": "#FCEAE8",
            "surfaceContainerHigh": "#F6E4E2",
            "surfaceContainerHighest": "#F1DEDC"
        },
        "dark": {
            "primary": "#FFB3AD",
            "surfaceTint": "#FFB3AD",
            "onPrimary": "#571E1B",
            "primaryContainer": "#73332F",
            "onPrimaryContainer": "#FFDAD6",
            "secondary": "#E7BDB9",
            "onSecondary": "#442927",
            "secondaryContainer": "#5D3F3D",
            "onSecondaryContainer": "#FFDAD6",
            "tertiary": "#E1C28C",
            "onTertiary": "#402D04",
            "tertiaryContainer": "#584319",
            "onTertiaryContainer": "#FFDEA6",
            "error": "#FFB4AB",
            "onError": "#690005",
            "errorContainer": "#93000A",
            "onErrorContainer": "#FFDAD6",
            "background": "#1A1110",
            "onBackground": "#F1DEDC",
            "surface": "#1A1110",
            "onSurface": "#F1DEDC",
            "surfaceVariant": "#534342",
            "onSurfaceVariant": "#D8C2BF",
            "outline": "#A08C8A",
            "outlineVariant": "#534342",
            "shadow": "#000000",
            "scrim": "#000000",
            "inverseSurface": "#F1DEDC",
            "inverseOnSurface": "#392E2D",
            "inversePrimary": "#904A45",
            "primaryFixed": "#FFDAD6",
            "onPrimaryFixed": "#3B0908",
            "primaryFixedDim": "#FFB3AD",
            "onPrimaryFixedVariant": "#73332F",
            "secondaryFixed": "#FFDAD6",
            "onSecondaryFixed": "#2C1513",
            "secondaryFixedDim": "#E7BDB9",
            "onSecondaryFixedVariant": "#5D3F3D",
            "tertiaryFixed": "#FFDEA6",
            "onTertiaryFixed": "#261900",
            "tertiaryFixedDim": "#E1C28C",
            "onTertiaryFixedVariant": "#584319",
            "surfaceDim": "#1A1110",
            "surfaceBright": "#423735",
            "surfaceContainerLowest": "#140C0B",
            "surfaceContainerLow": "#231918",
            "surfaceContainer": "#271D1C",
            "surfaceContainerHigh": "#322827",
            "surfaceContainerHighest": "#3D3231"
        },
        "dark-medium-contrast": {
            "primary": "#FFB9B3",
            "surfaceTint": "#FFB3AD",
            "onPrimary": "#330405",
            "primaryContainer": "#CC7B74",
            "onPrimaryContainer": "#000000",
            "secondary": "#EBC1BD",
            "onSecondary": "#26100E",
            "secondaryContainer": "#AD8884",
            "onSecondaryContainer": "#000000",
            "tertiary": "#E6C790",
            "onTertiary": "#201400",
            "tertiaryContainer": "#A88D5B",
            "onTertiaryContainer": "#000000",
            "error": "#FFBAB1",
            "onError": "#370001",
            "errorContainer": "#FF5449",
            "onErrorContainer": "#000000",
            "background": "#1A1110",
            "onBackground": "#F1DEDC",
            "surface": "#1A1110",
            "onSurface": "#FFF9F9",
            "surfaceVariant": "#534342",
            "onSurfaceVariant": "#DCC6C3",
            "outline": "#B39E9C",
            "outlineVariant": "#927F7D",
            "shadow": "#000000",
            "scrim": "#000000",
            "inverseSurface": "#F1DEDC",
            "inverseOnSurface": "#322827",
            "inversePrimary": "#743430",
            "primaryFixed": "#FFDAD6",
            "onPrimaryFixed": "#2C0102",
            "primaryFixedDim": "#FFB3AD",
            "onPrimaryFixedVariant": "#5E2320",
            "secondaryFixed": "#FFDAD6",
            "onSecondaryFixed": "#200B09",
            "secondaryFixedDim": "#E7BDB9",
            "onSecondaryFixedVariant": "#4B2F2D",
            "tertiaryFixed": "#FFDEA6",
            "onTertiaryFixed": "#190F00",
            "tertiaryFixedDim": "#E1C28C",
            "onTertiaryFixedVariant": "#463309",
            "surfaceDim": "#1A1110",
            "surfaceBright": "#423735",
            "surfaceContainerLowest": "#140C0B",
            "surfaceContainerLow": "#231918",
            "surfaceContainer": "#271D1C",
            "surfaceContainerHigh": "#322827",
            "surfaceContainerHighest": "#3D3231"
        },
        "dark-high-contrast": {
            "primary": "#FFF9F9",
            "surfaceTint": "#FFB3AD",
            "onPrimary": "#000000",
            "primaryContainer": "#FFB9B3",
            "onPrimaryContainer": "#000000",
            "secondary": "#FFF9F9",
            "onSecondary": "#000000",
            "secondaryContainer": "#EBC1BD",
            "onSecondaryContainer": "#000000",
            "tertiary": "#FFFAF7",
            "onTertiary": "#000000",
            "tertiaryContainer": "#E6C790",
            "onTertiaryContainer": "#000000",
            "error": "#FFF9F9",
            "onError": "#000000",
            "errorContainer": "#FFBAB1",
            "onErrorContainer": "#000000",
            "background": "#1A1110",
            "onBackground": "#F1DEDC",
            "surface": "#1A1110",
            "onSurface": "#FFFFFF",
            "surfaceVariant": "#534342",
            "onSurfaceVariant": "#FFF9F9",
            "outline": "#DCC6C3",
            "outlineVariant": "#DCC6C3",
            "shadow": "#000000",
            "scrim": "#000000",
            "inverseSurface": "#F1DEDC",
            "inverseOnSurface": "#000000",
            "inversePrimary": "#4E1715",
            "primaryFixed": "#FFE0DD",
            "onPrimaryFixed": "#000000",
            "primaryFixedDim": "#FFB9B3",
            "onPrimaryFixedVariant": "#330405",
            "secondaryFixed": "#FFE0DD",
            "onSecondaryFixed": "#000000",
            "secondaryFixedDim": "#EBC1BD",
            "onSecondaryFixedVariant": "#26100E",
            "tertiaryFixed": "#FFE3B5",
            "onTertiaryFixed": "#000000",
            "tertiaryFixedDim": "#E6C790",
            "onTertiaryFixedVariant": "#201400",
            "surfaceDim": "#1A1110",
            "surfaceBright": "#423735",
            "surfaceContainerLowest": "#140C0B",
            "surfaceContainerLow": "#231918",
            "surfaceContainer": "#271D1C",
            "surfaceContainerHigh": "#322827",
            "surfaceContainerHighest": "#3D3231"
        }
    },
    "palettes": {
        "primary": {
            "0": "#000000",
            "5": "#2D0002",
            "10": "#410003",
            "15": "#540006",
            "20": "#680009",
            "25": "#7D000D",
            "30": "#930011",
            "35": "#A90016",
            "40": "#BD0D1D",
            "50": "#E22F33",
            "60": "#FF544F",
            "70": "#FF8981",
            "80": "#FFB3AD",
            "90": "#FFDAD6",
            "95": "#FFEDEB",
            "98": "#FFF8F7",
            "99": "#FFFBFF",
            "100": "#FFFFFF"
        },
        "secondary": {
            "0": "#000000",
            "5": "#280404",
            "10": "#370D0C",
            "15": "#441815",
            "20": "#51221F",
            "25": "#5F2D29",
            "30": "#6C3734",
            "35": "#7A433F",
            "40": "#884E4A",
            "50": "#A56661",
            "60": "#C27F7A",
            "70": "#E09993",
            "80": "#FFB4AD",
            "90": "#FFDAD6",
            "95": "#FFEDEB",
            "98": "#FFF8F7",
            "99": "#FFFBFF",
            "100": "#FFFFFF"
        },
        "tertiary": {
            "0": "#000000",
            "5": "#190F00",
            "10": "#261900",
            "15": "#332300",
            "20": "#412D00",
            "25": "#4F3700",
            "30": "#5D4200",
            "35": "#6C4D00",
            "40": "#7B5800",
            "50": "#9A7000",
            "60": "#B78922",
            "70": "#D5A33C",
            "80": "#F3BE54",
            "90": "#FFDEA5",
            "95": "#FFEFD7",
            "98": "#FFF8F3",
            "99": "#FFFBFF",
            "100": "#FFFFFF"
        },
        "neutral": {
            "0": "#000000",
            "5": "#15100F",
            "10": "#201A19",
            "15": "#2B2424",
            "20": "#362F2E",
            "25": "#413A39",
            "30": "#4D4544",
            "35": "#595050",
            "40": "#655C5B",
            "50": "#7F7574",
            "60": "#998E8D",
            "70": "#B4A9A7",
            "80": "#D0C4C2",
            "90": "#EDE0DE",
            "95": "#FBEEEC",
            "98": "#FFF8F7",
            "99": "#FFFBFF",
            "100": "#FFFFFF"
        },
        "neutral-variant": {
            "0": "#000000",
            "5": "#190E0D",
            "10": "#251917",
            "15": "#302321",
            "20": "#3B2D2C",
            "25": "#473837",
            "30": "#534342",
            "35": "#5F4F4D",
            "40": "#6B5A59",
            "50": "#857371",
            "60": "#A08C8A",
            "70": "#BBA6A4",
            "80": "#D8C2BF",
            "90": "#F5DDDB",
            "95": "#FFEDEB",
            "98": "#FFF8F7",
            "99": "#FFFBFF",
            "100": "#FFFFFF"
        }
    }
}